grantme/__init__.py
grantme/main.py
grantme/procedures.py
grantme/constants/__init__.py
grantme/constants/misc.py
grantme/constants/msgs.py
grantme/constants/sqls.py
grantme/utils/__init__.py
grantme/utils/errors.py
grantme/utils/printers.py
grantme/utils/setup.py
grantme/utils/timer.py
tests/__init__.py
tests/test_single_user.py
tests/test_two_user.py
grantme-0.1.0.dist-info/LICENSE
grantme-0.1.0.dist-info/METADATA
grantme-0.1.0.dist-info/WHEEL
grantme-0.1.0.dist-info/entry_points.txt
grantme-0.1.0.dist-info/top_level.txt
grantme-0.1.0.dist-info/RECORD
