Metadata-Version: 2.1
Name: grantme
Version: 0.1.0
Summary: A noncompulsory access management CLI tool for shared machines.
Home-page: https://github.com/chuzhe-as-a-dev/grantme
Author: Chuzhe Tang
Author-email: t.chuzhe@qq.com
License: MIT
Project-URL: Bug Tracker, https://github.com/chuzhe-as-a-dev/grantme/issues
Platform: UNKNOWN
Classifier: Development Status :: 4 - Beta
Classifier: Intended Audience :: Developers
Classifier: Topic :: System :: Systems Administration
Classifier: Topic :: Utilities
Classifier: License :: OSI Approved :: MIT License
Classifier: Programming Language :: Python
Classifier: Programming Language :: Python :: 3
Classifier: Programming Language :: Python :: 3.7
Requires-Python: >=3.7
License-File: LICENSE
